{"organisasjonsnummer": "826157062", "navn": "L\u00c6RINGSVERKSTEDET GRUPPEN AS", "organisasjonsform": {"kode": "AS", "beskrivelse": "Aksjeselskap", "_links": {"self": {"href": "https://data.brreg.no/enhetsregisteret/api/organisasjonsformer/AS"}}}, "postadresse": {"land": "Norge", "landkode": "NO", "postnummer": "2051", "poststed": "JESSHEIM", "adresse": ["Postboks 215"], "kommune": "ULLENSAKER", "kommunenummer": "3209"}, "registreringsdatoEnhetsregisteret": "2020-12-10", "registrertIMvaregisteret": true, "naeringskode1": {"kode": "88.911", "beskrivelse": "Barnehager"}, "hjelpeenhetskode": {"kode": "70.100", "beskrivelse": "Hovedkontortjenester"}, "antallAnsatte": 67, "harRegistrertAntallAnsatte": true, "forretningsadresse": {"land": "Norge", "landkode": "NO", "postnummer": "2069", "poststed": "JESSHEIM", "adresse": ["Aktivitetsvegen 2"], "kommune": "ULLENSAKER", "kommunenummer": "3209"}, "stiftelsesdato": "2020-10-13", "institusjonellSektorkode": {"kode": "2100", "beskrivelse": "Private aksjeselskaper mv."}, "registrertIForetaksregisteret": true, "registrertIStiftelsesregisteret": false, "registrertIFrivillighetsregisteret": false, "sisteInnsendteAarsregnskap": "2022", "konkurs": false, "underAvvikling": false, "underTvangsavviklingEllerTvangsopplosning": false, "maalform": "Bokm\u00e5l", "vedtektsdato": "2020-12-18", "vedtektsfestetFormaal": ["Prosjektere og oppf\u00f8re barnehager. Videre skal selskapet forvalte", "eierskap til barnehager, samt yte tjenester til utvikling og drift av", "barnehager."], "aktivitet": ["Prosjektere og oppf\u00f8re barnehager. Videre skal selskapet forvalte", "eierskap til barnehager, samt yte tjenester til utvikling og drift av", "barnehager."], "_links": {"self": {"href": "https://data.brreg.no/enhetsregisteret/api/enheter/826157062"}}}