{"organisasjonsnummer": "919147857", "navn": "LOFOTEN INDUSTRI AS", "organisasjonsform": {"kode": "AS", "beskrivelse": "Aksjeselskap", "_links": {"self": {"href": "https://data.brreg.no/enhetsregisteret/api/organisasjonsformer/AS"}}}, "hjemmeside": "www.lofoten-industri.no", "postadresse": {"land": "Norge", "landkode": "NO", "postnummer": "8301", "poststed": "SVOLV\u00c6R", "adresse": ["Postboks 150"], "kommune": "V\u00c5GAN", "kommunenummer": "1865"}, "registreringsdatoEnhetsregisteret": "1995-02-19", "registrertIMvaregisteret": true, "naeringskode1": {"kode": "88.993", "beskrivelse": "Arbeidstrening for ordin\u00e6rt arbeidsmarked"}, "naeringskode2": {"kode": "88.911", "beskrivelse": "Barnehager"}, "naeringskode3": {"kode": "38.320", "beskrivelse": "Sortering og bearbeiding av avfall for materialgjenvinning"}, "antallAnsatte": 55, "harRegistrertAntallAnsatte": true, "forretningsadresse": {"land": "Norge", "landkode": "NO", "postnummer": "8300", "poststed": "SVOLV\u00c6R", "adresse": ["Vorset\u00f8yveien 18"], "kommune": "V\u00c5GAN", "kommunenummer": "1865"}, "stiftelsesdato": "1972-07-05", "institusjonellSektorkode": {"kode": "1520", "beskrivelse": "Kommunalt eide aksjeselskaper mv."}, "registrertIForetaksregisteret": true, "registrertIStiftelsesregisteret": false, "registrertIFrivillighetsregisteret": false, "sisteInnsendteAarsregnskap": "2022", "konkurs": false, "underAvvikling": false, "underTvangsavviklingEllerTvangsopplosning": false, "maalform": "Bokm\u00e5l", "vedtektsdato": "2006-06-09", "vedtektsfestetFormaal": ["P\u00e5 forretningsmessig basis \u00e5 drive yrkesrettet oppl\u00e6ring og", "kvalifisering av personer under attf\u00f8ring."], "aktivitet": ["\u00c5 drive fabrikasjon, omsetning og annen virksomhet", "som kan \u00f8ke mulighetene for sysselsetting av", "yrkesvalghemmede og mindre arbeidsf\u00f8re, fortrinns-", "vis fra Lofoten."], "_links": {"self": {"href": "https://data.brreg.no/enhetsregisteret/api/enheter/919147857"}}}