{"organisasjonsnummer": "971340355", "navn": "NORD-J\u00c6REN SPORTSDANSEKLUBB", "organisasjonsform": {"kode": "FLI", "beskrivelse": "Forening/lag/innretning", "_links": {"self": {"href": "https://data.brreg.no/enhetsregisteret/api/organisasjonsformer/FLI"}}}, "hjemmeside": "www.njs.no", "registreringsdatoEnhetsregisteret": "1995-02-20", "registrertIMvaregisteret": false, "naeringskode1": {"kode": "93.120", "beskrivelse": "Idrettslag og -klubber"}, "antallAnsatte": 11, "harRegistrertAntallAnsatte": true, "forretningsadresse": {"land": "Norge", "landkode": "NO", "postnummer": "4016", "poststed": "STAVANGER", "adresse": ["Hillev\u00e5gsveien 70"], "kommune": "STAVANGER", "kommunenummer": "1103"}, "stiftelsesdato": "1986-10-20", "institusjonellSektorkode": {"kode": "7000", "beskrivelse": "Ideelle organisasjoner"}, "registrertIForetaksregisteret": false, "registrertIStiftelsesregisteret": false, "registrertIFrivillighetsregisteret": true, "konkurs": false, "underAvvikling": false, "underTvangsavviklingEllerTvangsopplosning": false, "maalform": "Bokm\u00e5l", "aktivitet": ["Danseklubb. Klubbens form\u00e5l er \u00e5 drive idrett organisert i Norges", "Idrettsforbund, samt ved samarbeid og kameratskap \u00e5 fremme dans i", "sunne idrettslige former."], "_links": {"self": {"href": "https://data.brreg.no/enhetsregisteret/api/enheter/971340355"}}}