{"organisasjonsnummer": "976662156", "navn": "KONGSBERG KOMMUNALE EIENDOM KF", "organisasjonsform": {"kode": "KF", "beskrivelse": "Kommunalt foretak", "_links": {"self": {"href": "https://data.brreg.no/enhetsregisteret/api/organisasjonsformer/KF"}}}, "hjemmeside": "www.kkekf.no", "registreringsdatoEnhetsregisteret": "1996-09-01", "registrertIMvaregisteret": true, "frivilligMvaRegistrertBeskrivelser": ["Utleier av bygg eller anlegg"], "naeringskode1": {"kode": "81.109", "beskrivelse": "Andre kombinerte tjenester tilknyttet eiendomsdrift"}, "antallAnsatte": 100, "harRegistrertAntallAnsatte": true, "overordnetEnhet": "942402465", "forretningsadresse": {"land": "Norge", "landkode": "NO", "postnummer": "3617", "poststed": "KONGSBERG", "adresse": ["Numedalsveien 114"], "kommune": "KONGSBERG", "kommunenummer": "3303"}, "stiftelsesdato": "2002-01-22", "institusjonellSektorkode": {"kode": "6500", "beskrivelse": "Kommuneforvaltningen"}, "registrertIForetaksregisteret": true, "registrertIStiftelsesregisteret": false, "registrertIFrivillighetsregisteret": false, "konkurs": false, "underAvvikling": false, "underTvangsavviklingEllerTvangsopplosning": false, "maalform": "Bokm\u00e5l", "vedtektsdato": "2010-08-18", "vedtektsfestetFormaal": ["Ivareta kommunens eier- og leierinteresser i den samlede", "eiendomsmassen for gjennom dette \u00e5 s\u00f8rge for at fellesskapets verdier", "beholdes og for at hensiktsmessige bygg/boliger/arealer stilles til", "disposisjon for vedtatt kommunal tjenesteproduksjon og for kommunal", "boligtildeling. Foretaket gir leietaker kun adgang til \u00e5 disponere", "lokaler/arealer etter inng\u00e5else av kontrakt. Kongsberg kommunale", "eiendom KF skal ikke ha noe \u00f8konomisk form\u00e5l utover \u00e5 bidra aktivt til", "en sunn kommunal eiendoms\u00f8konomi og derigjennom en sunn", "kommune\u00f8konomi. St\u00e5 ansvarlig for en eiendoms\u00f8konomisk og", "forskriftsmessig forvaltning, drift, vedlikehold, byggutvikling og", "serviceytelse (FDVUS) av eiendommene, samt utvikling, avhending og", "kompletering av eiendomsmassen. Ivareta byggherrefunksjonen ved", "utbygging p\u00e5 vegne av kommunens tjenesteenheter. V\u00e6re kommunens", "kompetansesenter innen eiendomsomr\u00e5det."], "aktivitet": ["Stille hensiktsmessige bygg/eiendom/arealer til disposisjon for", "tjenesteproduksjon i Kongsberg kommune og FDVUS (Forvaltning, Drift,", "Vedlikehold, Service) av disse."], "_links": {"self": {"href": "https://data.brreg.no/enhetsregisteret/api/enheter/976662156"}, "overordnetEnhet": {"href": "https://data.brreg.no/enhetsregisteret/api/enheter/942402465"}}}