{"organisasjonsnummer": "976987403", "navn": "NORDBERG SOKN", "organisasjonsform": {"kode": "KIRK", "beskrivelse": "Den norske kirke", "_links": {"self": {"href": "https://data.brreg.no/enhetsregisteret/api/organisasjonsformer/KIRK"}}}, "hjemmeside": "www.kirken.no/Nordberg", "registreringsdatoEnhetsregisteret": "1997-01-27", "registrertIMvaregisteret": false, "naeringskode1": {"kode": "94.910", "beskrivelse": "Religi\u00f8se organisasjoner"}, "naeringskode2": {"kode": "88.911", "beskrivelse": "Barnehager"}, "antallAnsatte": 29, "harRegistrertAntallAnsatte": true, "forretningsadresse": {"land": "Norge", "landkode": "NO", "postnummer": "0861", "poststed": "OSLO", "adresse": ["Kringsj\u00e5grenda 1"], "kommune": "OSLO", "kommunenummer": "0301"}, "institusjonellSektorkode": {"kode": "6500", "beskrivelse": "Kommuneforvaltningen"}, "registrertIForetaksregisteret": false, "registrertIStiftelsesregisteret": false, "registrertIFrivillighetsregisteret": false, "konkurs": false, "underAvvikling": false, "underTvangsavviklingEllerTvangsopplosning": false, "maalform": "Bokm\u00e5l", "aktivitet": ["Sokn"], "_links": {"self": {"href": "https://data.brreg.no/enhetsregisteret/api/enheter/976987403"}}}