{"organisasjonsnummer": "985046646", "navn": "MILJ\u00d8TUN AS", "organisasjonsform": {"kode": "AS", "beskrivelse": "Aksjeselskap", "_links": {"self": {"href": "https://data.brreg.no/enhetsregisteret/api/organisasjonsformer/AS"}}}, "registreringsdatoEnhetsregisteret": "2002-12-02", "registrertIMvaregisteret": false, "naeringskode1": {"kode": "68.209", "beskrivelse": "Utleie av egen eller leid fast eiendom ellers"}, "harRegistrertAntallAnsatte": true, "forretningsadresse": {"land": "Norge", "landkode": "NO", "postnummer": "6065", "poststed": "ULSTEINVIK", "adresse": ["Varleiter\u00e5sa 7"], "kommune": "ULSTEIN", "kommunenummer": "1516"}, "stiftelsesdato": "2002-10-22", "institusjonellSektorkode": {"kode": "2100", "beskrivelse": "Private aksjeselskaper mv."}, "registrertIForetaksregisteret": true, "registrertIStiftelsesregisteret": false, "registrertIFrivillighetsregisteret": false, "sisteInnsendteAarsregnskap": "2022", "konkurs": false, "underAvvikling": false, "underTvangsavviklingEllerTvangsopplosning": false, "maalform": "Nynorsk", "vedtektsdato": "2020-12-08", "vedtektsfestetFormaal": ["Utleige av eigedom samt deltaking i andre selskaper med \u00f8konomisk", "gevinst som form\u00e5l."], "aktivitet": ["Drift av eigedom - eigedomsselskap."], "_links": {"self": {"href": "https://data.brreg.no/enhetsregisteret/api/enheter/985046646"}}}