{"organisasjonsnummer": "992208430", "navn": "BANEVEIEN BARNEHAGE AS", "organisasjonsform": {"kode": "AS", "beskrivelse": "Aksjeselskap", "_links": {"self": {"href": "https://data.brreg.no/enhetsregisteret/api/organisasjonsformer/AS"}}}, "postadresse": {"land": "Norge", "landkode": "NO", "postnummer": "1743", "poststed": "KLAVESTADHAUGEN", "adresse": ["Bodals vei 2C"], "kommune": "SARPSBORG", "kommunenummer": "3105"}, "registreringsdatoEnhetsregisteret": "2008-01-31", "registrertIMvaregisteret": false, "naeringskode1": {"kode": "88.911", "beskrivelse": "Barnehager"}, "antallAnsatte": 33, "harRegistrertAntallAnsatte": true, "forretningsadresse": {"land": "Norge", "landkode": "NO", "postnummer": "1738", "poststed": "BORGENHAUGEN", "adresse": ["Baneveien 20E"], "kommune": "SARPSBORG", "kommunenummer": "3105"}, "stiftelsesdato": "2008-01-08", "institusjonellSektorkode": {"kode": "2100", "beskrivelse": "Private aksjeselskaper mv."}, "registrertIForetaksregisteret": true, "registrertIStiftelsesregisteret": false, "registrertIFrivillighetsregisteret": false, "sisteInnsendteAarsregnskap": "2022", "konkurs": false, "underAvvikling": false, "underTvangsavviklingEllerTvangsopplosning": false, "maalform": "Bokm\u00e5l", "vedtektsdato": "2023-09-12", "vedtektsfestetFormaal": ["Barnehagevirksomhet."], "aktivitet": ["Drift av barnehager."], "_links": {"self": {"href": "https://data.brreg.no/enhetsregisteret/api/enheter/992208430"}}}